ratehawk_sdk/__init__.py
ratehawk_sdk/config.py
ratehawk_sdk/sdk.py
jaalvarez2818_ratehawk_sdk-0.2.0.dist-info/METADATA
jaalvarez2818_ratehawk_sdk-0.2.0.dist-info/WHEEL
jaalvarez2818_ratehawk_sdk-0.2.0.dist-info/top_level.txt
jaalvarez2818_ratehawk_sdk-0.2.0.dist-info/RECORD
